beetsplug/__init__.py
beetsplug/mpd-queue.py
mpd_queue-1.0.5.dist-info/LICENSE
mpd_queue-1.0.5.dist-info/METADATA
mpd_queue-1.0.5.dist-info/WHEEL
mpd_queue-1.0.5.dist-info/top_level.txt
mpd_queue-1.0.5.dist-info/RECORD
